{
  "annotations": {
    "changelogDate": "20251108154020"
  },
  "applications": "*",
  "dto": "mapstruct",
  "fields": [
    {
      "fieldName": "id",
      "fieldType": "Long",
      "fieldValidateRules": ["required", "unique"]
    },
    {
      "fieldName": "titulo",
      "fieldType": "String",
      "fieldValidateRules": ["required", "maxlength"],
      "fieldValidateRulesMaxlength": "200"
    },
    {
      "fieldName": "resumen",
      "fieldType": "String",
      "fieldValidateRules": ["required", "maxlength"],
      "fieldValidateRulesMaxlength": "500"
    },
    {
      "fieldName": "descripcion",
      "fieldType": "TextBlob",
      "fieldValidateRules": ["required"]
    },
    {
      "fieldName": "fecha",
      "fieldType": "Instant",
      "fieldValidateRules": ["required"]
    },
    {
      "fieldName": "direccion",
      "fieldType": "String",
      "fieldValidateRules": ["required", "maxlength"],
      "fieldValidateRulesMaxlength": "300"
    },
    {
      "fieldName": "imagen",
      "fieldType": "String",
      "fieldValidateRules": ["maxlength"],
      "fieldValidateRulesMaxlength": "1000"
    },
    {
      "fieldName": "filaAsientos",
      "fieldType": "Integer",
      "fieldValidateRules": ["required", "min"],
      "fieldValidateRulesMin": "1"
    },
    {
      "fieldName": "columnAsientos",
      "fieldType": "Integer",
      "fieldValidateRules": ["required", "min"],
      "fieldValidateRulesMin": "1"
    },
    {
      "fieldName": "precioEntrada",
      "fieldType": "BigDecimal",
      "fieldValidateRules": ["required", "min"],
      "fieldValidateRulesMin": "0"
    }
  ],
  "name": "Evento",
  "pagination": "pagination",
  "relationships": [
    {
      "otherEntityField": "nombre",
      "otherEntityName": "eventoTipo",
      "relationshipName": "eventoTipo",
      "relationshipSide": "left",
      "relationshipType": "one-to-one",
      "relationshipValidateRules": "required"
    },
    {
      "otherEntityField": "nombre",
      "otherEntityName": "integrante",
      "otherEntityRelationshipName": "eventos",
      "relationshipName": "integrantes",
      "relationshipSide": "left",
      "relationshipType": "many-to-many"
    }
  ],
  "searchEngine": "no",
  "service": "serviceImpl"
}
